majorgroove/__init__.py
majorgroove/client.py
majorgroove/constraints.py
majorgroove/export.py
majorgroove/models.py
majorgroove/parser.py
majorgroove-0.3.0.dist-info/METADATA
majorgroove-0.3.0.dist-info/WHEEL
majorgroove-0.3.0.dist-info/top_level.txt
majorgroove-0.3.0.dist-info/RECORD
