Metadata-Version: 2.4
Name: majorgroove
Version: 0.3.0
Summary: Python client for the MajorGroove API
Author: Tapdance DNA
License: MIT
Project-URL: Homepage, https://github.com/tapdance-dna/majorgroove
Project-URL: Issues, https://github.com/tapdance-dna/majorgroove/issues
Requires-Python: >=3.9
Requires-Dist: requests>=2.31.0
